errand/__init__.py
errand/backend.py
errand/compiler.py
errand/context.py
errand/cpp.py
errand/cuda_hip.py
errand/fortran.py
errand/gofers.py
errand/openacc_cpp.py
errand/order.py
errand/pthread.py
errand/system.py
errand/util.py
errand/workshop.py
errand-0.2.10.dist-info/LICENSE
errand-0.2.10.dist-info/METADATA
errand-0.2.10.dist-info/WHEEL
errand-0.2.10.dist-info/top_level.txt
errand-0.2.10.dist-info/RECORD
